import_parent_dir/__init__.py
import_parent_dir-0.1.1.dist-info/DESCRIPTION.rst
import_parent_dir-0.1.1.dist-info/METADATA
import_parent_dir-0.1.1.dist-info/RECORD
import_parent_dir-0.1.1.dist-info/WHEEL
import_parent_dir-0.1.1.dist-info/metadata.json
import_parent_dir-0.1.1.dist-info/top_level.txt
